detective_tools/__init__.py
detective_tools/df_snapshot.py
detective_tools/report.py
detective_tools/schema_versioning.py
detective_tools/snapshot_base.py
detective_tools/snapshot_diff.py
detective_tools/snapshot_history.py
drift_detective-0.1.0.dist-info/licenses/LICENSE
drift_detective-0.1.0.dist-info/METADATA
drift_detective-0.1.0.dist-info/WHEEL
drift_detective-0.1.0.dist-info/top_level.txt
drift_detective-0.1.0.dist-info/RECORD
