Metadata-Version: 2.4
Name: drift-detective
Version: 0.1.0
Summary: A Python utility for DataFrame snapshots, schema tracking, and drift detection
Author-email: Daniel Varga <email@example.com>
Project-URL: Homepage, https://github.com/danielv089
Project-URL: Repository, https://github.com/danielv089/drift-detective
Project-URL: Documentation, https://github.com/danielv089/drift-detective/blob/main/docs/DOCUMENTATION.md
Project-URL: Changelog, https://github.com/danielv089/drift-detective/blob/main/CHANGELOG.md
Keywords: dataframe,snapshot,schema,drift,pandas,data engineering
Requires-Python: >=3.10
License-File: LICENSE
Requires-Dist: pandas>=2.0
Provides-Extra: dev
Requires-Dist: pytest>=8.0; extra == "dev"
Requires-Dist: black; extra == "dev"
Requires-Dist: mypy; extra == "dev"
Requires-Dist: flake8; extra == "dev"
Dynamic: license-file
